diamond/__init__.py
diamond/diamond.py
diamondpy-0.0.2.dist-info/METADATA
diamondpy-0.0.2.dist-info/WHEEL
diamondpy-0.0.2.dist-info/top_level.txt
diamondpy-0.0.2.dist-info/RECORD
