Metadata-Version: 2.1
Name: diamondpy
Version: 0.0.2
Summary: A python game changer.
Home-page: https://github.com/pypa/sampleproject
Author: Ethan Burgos
Author-email: ethanburgos010@gmail.com
License: UNKNOWN
Project-URL: Bug Tracker, https://github.com/pypa/sampleproject/issues
Platform: UNKNOWN
Classifier: Programming Language :: Python :: 3
Classifier: License :: OSI Approved :: MIT License
Classifier: Operating System :: OS Independent
Requires-Python: >=3.6
Requires-Dist: sly
